<?xml version="1.0" encoding="UTF-8" standalone="yes"?>
<node artifactManager="be.nabu.eai.module.services.vm.VMServiceManager" created="2022-02-17T13:38:51.206+01:00" lastModified="2022-03-16T15:55:34.215+01:00" leaf="true" version="14">
    <environmentId>apollo</environmentId>
    <hidden>false</hidden>
    <properties/>
    <references>nabu.utils.List.size</references>
    <references>nabu.frameworks.io.database.types.channelInstanceData</references>
    <references>nabu.frameworks.io.database.types.channel</references>
    <references>java.util.UUID</references>
    <references>nabu.frameworks.io.services.runProvider</references>
</node>
